Metadata-Version: 2.4
Name: beancount_reds_plugins
Version: 0.4.0
Summary: A collection of plugins for Beancount
Home-page: https://github.com/redstreet/beancount_reds_plugins
Author: Red Street
Author-email: redstreet@users.noreply.github.com
License: GPL-3.0
Keywords: plugins double-entry banking beancount accounting
Classifier: Development Status :: 4 - Beta
Classifier: Intended Audience :: Financial and Insurance Industry
Classifier: License :: OSI Approved :: GNU General Public License v3 (GPLv3)
Classifier: Natural Language :: English
Classifier: Programming Language :: Python :: 3 :: Only
Classifier: Programming Language :: Python :: 3.6
Classifier: Topic :: Office/Business :: Financial :: Accounting
Classifier: Topic :: Office/Business :: Financial :: Investment
License-File: LICENSE
Requires-Dist: beancount>=2.2.3
Dynamic: author
Dynamic: author-email
Dynamic: classifier
Dynamic: description
Dynamic: description-content-type
Dynamic: home-page
Dynamic: keywords
Dynamic: license
Dynamic: license-file
Dynamic: requires-dist
Dynamic: summary
